setup.py
dynamixel/__init__.py
dynamixel/defs.py
dynamixel/dynamixel.py
dynamixel/dynamixel_network.py
dynamixel/echo_stream.py
dynamixel/enumeration.py
dynamixel/event_handler.py
dynamixel/serial_stream.py
dynamixel/stream.py
dynamixel/tests.py
dynamixel.egg-info/PKG-INFO
dynamixel.egg-info/SOURCES.txt
dynamixel.egg-info/dependency_links.txt
dynamixel.egg-info/requires.txt
dynamixel.egg-info/top_level.txt