Metadata-Version: 1.0
Name: dynamixel
Version: 1.0.3
Summary: Dynamixel Servo Library
Home-page: http://github.com/iandanforth/pydynamixel
Author: Ian Danforth
Author-email: iandanforth@gmail.com
License: GPL
Download-URL: http://cloud.github.com/downloads/iandanforth/pydynamixel/dynamixel-1.0.3.tar.gz
Keywords: dynamixel,robotis,ax-12
Platform: UNKNOWN
Classifier: Environment :: Console
Classifier: Intended Audience :: Developers
Classifier: Programming Language :: Python
